SkyStaticAnalysis/__init__.py
SkyStaticAnalysis/__main__.py
SkyStaticAnalysis/clang_utils/__init__.py
SkyStaticAnalysis/clang_utils/code_attributes/__init__.py
SkyStaticAnalysis/clang_utils/code_attributes/extract_function_info.py
SkyStaticAnalysis/clang_utils/code_attributes/extract_globals.py
SkyStaticAnalysis/clang_utils/code_attributes/extract_statement_info.py
SkyStaticAnalysis/clang_utils/code_attributes/utils.py
SkyStaticAnalysis/third_parties/__init__.py
SkyStaticAnalysis/third_parties/cfg_extractor/__init__.py
SkyStaticAnalysis/third_parties/cfg_extractor/cfg.py
SkyStaticAnalysis/third_parties/cfg_extractor/cfgblock.py
SkyStaticAnalysis/third_parties/cfg_extractor/customvector.py
SkyStaticAnalysis/third_parties/cfg_extractor/utils.py
SkyStaticAnalysis/third_parties/cfg_extractor/decorators/__init__.py
SkyStaticAnalysis/third_parties/cfg_extractor/decorators/ast_node_decorator.py
SkyStaticAnalysis/third_parties/cfg_extractor/decorators/concrete_node_decorators.py
SkyStaticAnalysis/third_parties/cfg_extractor/decorators/enumeration.py
SkyStaticAnalysis/third_parties/jsonobject/__init__.py
SkyStaticAnalysis/third_parties/jsonobject/api.py
SkyStaticAnalysis/third_parties/jsonobject/base.py
SkyStaticAnalysis/third_parties/jsonobject/base_properties.py
SkyStaticAnalysis/third_parties/jsonobject/containers.py
SkyStaticAnalysis/third_parties/jsonobject/exceptions.py
SkyStaticAnalysis/third_parties/jsonobject/properties.py
SkyStaticAnalysis/third_parties/jsonobject/utils.py
SkyStaticAnalysis/utils/__init__.py
SkyStaticAnalysis/utils/functional.py
SkyStaticAnalysis-0.0.4.dist-info/LICENSE.txt
SkyStaticAnalysis-0.0.4.dist-info/METADATA
SkyStaticAnalysis-0.0.4.dist-info/WHEEL
SkyStaticAnalysis-0.0.4.dist-info/top_level.txt
SkyStaticAnalysis-0.0.4.dist-info/RECORD
