Metadata-Version: 2.1
Name: SkyStaticAnalysis
Version: 0.0.4
Summary: A pure-python (Python>=3.10) static analysis library providing various interfaces.
Home-page: https://github.com/hzyrc6011/skystaticanalysis
Author: hzyrc6011
Author-email: 1295752786@qq.com
License: MIT
Project-URL: Documentation, https://hzyrc6011.github.io/skystaticanalysis/
Classifier: Development Status :: 3 - Alpha
Classifier: Intended Audience :: Science/Research
Classifier: License :: OSI Approved :: MIT License
Classifier: Natural Language :: English
Classifier: Operating System :: Unix
Classifier: Operating System :: Microsoft :: Windows
Classifier: Programming Language :: Python :: 3.10
Classifier: Programming Language :: Python :: 3.11
Classifier: Programming Language :: Python :: 3.12
Classifier: Topic :: Software Development
Classifier: Topic :: Software Development :: Libraries :: Python Modules
Requires-Python: >=3.10
License-File: LICENSE.txt
Requires-Dist: clang ~=16.0
Requires-Dist: libclang ~=16.0
Requires-Dist: six
